litendb/table.py
litendb/lib.pyx
litendb/__init__.py
litendb/cache.py
litendb/lib.pxd
litendb/app.py
litendb/utils.py
litendb/service.py
litendb/schema.py
litendb/libliten.so
litendb/lib.cpython-312-x86_64-linux-gnu.so
litendb/version.py
litendb/includes/ctcache.pxd
litendb/includes/__init__.pxd
litendb.libs/libgflags-288df2ca.so.2.2.2
litendb.libs/libglog-cc080fc1.so.0.6.0
litendb.libs/libliten-6b68e537.so
litendb.libs/libunwind-28e77a49.so.8.0.1
litendb.libs/libtbb-68dc33c6.so.12
litendb.libs/libarrow-80f87fc8.so.2100.0.0
litendb.libs/liblzma-a9793942.so.5.4.5
litendb-0.0.13.dist-info/WHEEL
litendb-0.0.13.dist-info/LICENSE
litendb-0.0.13.dist-info/METADATA
litendb-0.0.13.dist-info/top_level.txt
litendb-0.0.13.dist-info/RECORD
