Metadata-Version: 2.1
Name: litendb
Version: 0.0.13
Summary: Big Data Analytics Toolset
Home-page: https://github.com/liten/
Author: HK Verma
Author-email: hkverma@gmail.com
Classifier: Programming Language :: Python :: 3
Classifier: License :: OSI Approved :: MIT License
Classifier: Operating System :: OS Independent
Requires-Python: >=3.12
License-File: LICENSE
Requires-Dist: numpy
Requires-Dist: cython ==3.1.4
Requires-Dist: pyarrow ==21.0.0
Requires-Dist: pandas
Requires-Dist: jupyterlab
Requires-Dist: graphviz
Requires-Dist: tbb-devel
Requires-Dist: pyspark ==3.5.3
Requires-Dist: seaborn
